__init__.py
api.py
cliprinter.py
handler.py
main.py
poller.py
screenupdater.py
tray.py
screen/__init__.py
screen/epd2in9b_V3.py
screen/epdconfig.py
screen/screen.py
co2monitor-2.2.dist-info/METADATA
co2monitor-2.2.dist-info/WHEEL
co2monitor-2.2.dist-info/entry_points.txt
co2monitor-2.2.dist-info/top_level.txt
co2monitor-2.2.dist-info/RECORD
