Metadata-Version: 2.4
Name: co2monitor
Version: 2.2
Summary: See the current co2 emissions per kWh of electricity in the Netherlands
Author: Rens Oliemans
License-Expression: GPL-3.0-or-later
Project-URL: Homepage, https://codeberg.org/rensoliemans/co2monitor
Project-URL: Changelog, https://codeberg.org/RensOliemans/co2monitor/src/branch/main/CHANGELOG.md
Classifier: Programming Language :: Python :: 3
Classifier: Programming Language :: Python :: 3.9
Classifier: Programming Language :: Python :: 3.10
Classifier: Programming Language :: Python :: 3.11
Classifier: Programming Language :: Python :: 3.12
Classifier: Programming Language :: Python :: 3.13
Requires-Python: >=3.9
Requires-Dist: click>=8.1.7
Requires-Dist: loguru>=0.6.0
Requires-Dist: python-dotenv>=1.0.1
Requires-Dist: requests>=2.32.2
Provides-Extra: tray
Requires-Dist: pyside6>=6.8.0.2; extra == "tray"
Provides-Extra: screen
Requires-Dist: pillow~=9.5; extra == "screen"
Requires-Dist: rpi.gpio>=0.7.1; extra == "screen"
Requires-Dist: spidev>=3.6; extra == "screen"
